starlette_early_data.py
starlette_early_data-1.1.0.data/data/LICENSE
starlette_early_data-1.1.0.dist-info/LICENSE
starlette_early_data-1.1.0.dist-info/METADATA
starlette_early_data-1.1.0.dist-info/WHEEL
starlette_early_data-1.1.0.dist-info/top_level.txt
starlette_early_data-1.1.0.dist-info/RECORD
