Metadata-Version: 2.1
Name: starlette-early-data
Version: 1.1.0
Summary: Middleware and decorator for processing TLSv1.3 early data requests in Starlette
Home-page: https://github.com/HarrySky/starlette-early-data
Author: Igor Nehoroshev
Author-email: mail@neigor.me
License: Unlicense
Platform: UNKNOWN
Classifier: Development Status :: 5 - Production/Stable
Classifier: Environment :: Web Environment
Classifier: Intended Audience :: Developers
Classifier: License :: Public Domain
Classifier: Operating System :: OS Independent
Classifier: Programming Language :: Python :: 3
Classifier: Programming Language :: Python :: 3.6
Classifier: Programming Language :: Python :: 3.7
Classifier: Programming Language :: Python :: 3.8
Requires-Python: >=3.6
Requires-Dist: starlette (>=0.12.11)
